odoo8_addon_l10n_es_location_nuts-8.0.1.0.0.99.dev10-py3.6-nspkg.pth
odoo_addons/l10n_es_location_nuts/README.rst
odoo_addons/l10n_es_location_nuts/__init__.py
odoo_addons/l10n_es_location_nuts/__openerp__.py
odoo_addons/l10n_es_location_nuts/hooks.py
odoo_addons/l10n_es_location_nuts/i18n/ca.po
odoo_addons/l10n_es_location_nuts/i18n/es.po
odoo_addons/l10n_es_location_nuts/i18n/l10n_es_location_nuts.pot
odoo_addons/l10n_es_location_nuts/static/description/icon.png
odoo_addons/l10n_es_location_nuts/wizard/__init__.py
odoo_addons/l10n_es_location_nuts/wizard/nuts_import.py
odoo8_addon_l10n_es_location_nuts-8.0.1.0.0.99.dev10.dist-info/METADATA
odoo8_addon_l10n_es_location_nuts-8.0.1.0.0.99.dev10.dist-info/WHEEL
odoo8_addon_l10n_es_location_nuts-8.0.1.0.0.99.dev10.dist-info/namespace_packages.txt
odoo8_addon_l10n_es_location_nuts-8.0.1.0.0.99.dev10.dist-info/top_level.txt
odoo8_addon_l10n_es_location_nuts-8.0.1.0.0.99.dev10.dist-info/RECORD
